<Defs xmlns:xsi="http://www.w3.org/2001/XMLSchema-instance" xsi:noNamespaceSchemaLocation="../../../../Schemas/MutationDef.xsd">
	<Pawnmorph.Hediffs.MutationDef Name ="FamiliarisJawPart" ParentName="CanidJawPart" Abstract="true">
		<mutationMemory>EtherFamiliarisJaw</mutationMemory>
	</Pawnmorph.Hediffs.MutationDef>

	<Pawnmorph.Hediffs.MutationDef Name ="FamiliarisEarPart" ParentName="CanidEarPart" Abstract="true">
		<mutationMemory>EtherFamiliarisEar</mutationMemory>
	</Pawnmorph.Hediffs.MutationDef>

	<Pawnmorph.Hediffs.MutationDef Name ="FamiliarisTailPart" ParentName="CanidTailPart" Abstract="true">
		<mutationMemory>EtherFamiliarisTail</mutationMemory>
	</Pawnmorph.Hediffs.MutationDef>
</Defs>