<Defs>
	<ThoughtDef>
		<defName>FurryMutationThoughtsHappy</defName> <!-- this is the default thougths for pawns that have mutations and have the furry trait  -->
		<workerClass>Pawnmorph.Thoughts.Worker_HasMutations</workerClass>
		<validWhileDespawned>true</validWhileDespawned>
		<requiredTraits>
			<li>MutationAffinity</li>
		</requiredTraits>
		<stages>
			<li>
				<label>TODO</label>  
				<description>TODO</description>
				<baseMoodEffect>4</baseMoodEffect>
			</li>
			<li> <!-- stages are evently split between human influence [0,1] -->
				<label>TODO</label>
				<description>TODO</description>
				<baseMoodEffect>7</baseMoodEffect>
			</li>
			<li>
				<label>TODO</label>
				<description>TODO</description>
				<baseMoodEffect>9</baseMoodEffect>
			</li>
			<li>
				<label>TODO</label>
				<description>TODO</description>
				<baseMoodEffect>11</baseMoodEffect>
			</li>
			<li>
				<label>TODO</label>
				<description>TODO</description>
				<baseMoodEffect>12</baseMoodEffect>
			</li>
			<li>
				<label>TODO</label>
				<description>TODO</description>
				<baseMoodEffect>13</baseMoodEffect>
			</li>
		</stages>
	</ThoughtDef>
</Defs>