<Defs xmlns:xsi="http://www.w3.org/2001/XMLSchema-instance" xsi:noNamespaceSchemaLocation="../../../../../Schemas/ThoughtDef.xsd">
    <ThoughtDef Name="PM_Precept_GuestTfBase" Abstract="true">
        <durationDays>10</durationDays>
    </ThoughtDef>

    <ThoughtDef ParentName="PM_Precept_GuestTfBase">
        <defName>PM_TfLovedPrecept_TransformationReaction</defName>
        <stages>
            <li>
                <label>transformed wild pawn</label>
                <description>Now they have truly returned to nature.</description>
				<baseMoodEffect>2</baseMoodEffect>
            </li>
            <li>
                <label>transformed colonist</label>
                <description>They are closer to nature now.</description>
                <baseMoodEffect>2</baseMoodEffect>
            </li>
            <li>
                <label>transformed prisoner</label>
                <description>Our prisoners should bend the knee to the natural world in their own form.</description>
                <baseMoodEffect>3</baseMoodEffect>
            </li>
            <li>
                <label>transformed guest</label>
                <description>Our guests are guests of the natural world, and they should look the part.</description>
                <baseMoodEffect>3</baseMoodEffect>
            </li>
            <li>
                <label>transformed slave</label>
                <description>A gift to the natural world.</description>
				<baseMoodEffect>1</baseMoodEffect>
            </li>
            <li>
                <label>transformed guilty prisoner</label>
                <description>Those that wrong us will serve the natural world once more.</description>
				<baseMoodEffect>5</baseMoodEffect>
            </li>
        </stages>
    </ThoughtDef>

    <ThoughtDef ParentName="PM_Precept_GuestTfBase">
        <defName>PM_TfLovedPrecept_MergedThought</defName>
        <stages>
            <li>
                <label>wild pawn merged</label>
                <description>TODO</description>
            </li>
            <li>
                <label>colonist merged</label>
                <description>TODO</description>
                <baseMoodEffect>-8</baseMoodEffect>

            </li>
            <li>
                <label>prisoner merged</label>
                <description>TODO</description>
                <baseMoodEffect>-4</baseMoodEffect>

            </li>
            <li>
                <label>guest merged</label>
                <description>TODO</description>
                <baseMoodEffect>-8</baseMoodEffect>
            </li>
        </stages>
    </ThoughtDef>


    <ThoughtDef ParentName="PM_Precept_GuestTfBase">
        <defName>PM_ReversionHatedPrecept_RevertedPawnReaction</defName>
        <stages>
            <li>
                <label>wild pawn reverted</label>
                <description>They should remain as they were.</description>
                <baseMoodEffect>-3</baseMoodEffect>
            </li>
            <li>
                <label>colonist reverted</label>
                <description>They should remain as they were.</description>
                <baseMoodEffect>-5</baseMoodEffect>
            </li>
            <li>
                <label>prisoner reverted</label>
                <description>They should remain as they were.</description>
                <baseMoodEffect>-3</baseMoodEffect>
            </li>
            <li>
                <label>guest reverted</label>
                <description>They should remain as they were.</description>
                <baseMoodEffect>-3</baseMoodEffect>
            </li>
        </stages>
    </ThoughtDef>

    <ThoughtDef ParentName="PM_Precept_GuestTfBase">
        <defName>PM_SapienceLossLikedPrecept_PermanentlyFeralReaction</defName>
        <stages>
            <li>
                <label>wild pawn permanently feral</label>
                <description>TODO</description>
                <baseMoodEffect>-1</baseMoodEffect>
            </li>
            <li>
                <label>colonist permanently feral</label>
                <description>TODO</description>
                <baseMoodEffect>-2</baseMoodEffect>
            </li>
            <li>
                <label>prisoner permanently feral</label>
                <description>Did we really expect to turn them back?</description>
                <visible>true</visible>
            </li>
            <li>
                <label>guest permanently feral</label>
                <description>TODO</description>
                <baseMoodEffect>-1</baseMoodEffect>
            </li>
        </stages>
    </ThoughtDef>

    <ThoughtDef ParentName="PM_Precept_GuestTfBase">
        <defName>PM_SapienceLossAbhorrentPrecept_PermanentlyFeralReaction</defName>
        <stages>
            <li>
                <label>wild pawn permanently feral</label>
                <description>TODO</description>
                <baseMoodEffect>-1</baseMoodEffect>
            </li>
            <li>
                <label>colonist permanently feral</label>
                <description>TODO</description>
                <baseMoodEffect>-2</baseMoodEffect>
            </li>
            <li>
                <label>prisoner permanently feral</label>
                <description>Did we really expect to turn them back?</description>
                <visible>true</visible>
            </li>
            <li>
                <label>guest permanently feral</label>
                <description>TODO</description>
                <baseMoodEffect>-1</baseMoodEffect>
            </li>
        </stages>
    </ThoughtDef>
</Defs>