<Defs>
	<HediffDef ParentName="MorphParent">
		<defName>PawnmorphSnakeTF</defName>
		<label>snakemorph</label>
		<stages>
			<li>
				<label>reeling</label>
				<hungerRateFactor>1.6</hungerRateFactor>
				<painOffset>0.05</painOffset>
				<capMods>
					<li>
						<capacity>Moving</capacity>
						<offset>-0.05</offset>
					</li>
				</capMods>
				<hediffGivers>
					<li Class="Pawnmorph.HediffGiver_TF">
						<hediff>TransformedHuman</hediff>
						<pawnkinds>
							<li>Cobra</li>
						</pawnkinds>
						<tale>TransformationMisc</tale>
					</li>
				</hediffGivers>
			</li>
			<li>
				<label>transforming</label>
				<minSeverity>0.6</minSeverity>
				<painOffset>0.1</painOffset>
				<vomitMtbDays>1</vomitMtbDays>
				<capMods>
					<li>
						<capacity>Moving</capacity>
						<offset>-0.05</offset>
					</li>
					<li>
						<capacity>Sight</capacity>
						<offset>-0.05</offset>
					</li>
					<li>
						<capacity>Manipulation</capacity>
						<offset>-0.05</offset>
					</li>
				</capMods>
			</li>
			<li>
				<label>changing</label>
				<minSeverity>0.65</minSeverity>
				<painOffset>0.1</painOffset>
				<vomitMtbDays>1</vomitMtbDays>
				<capMods>
					<li>
						<capacity>Moving</capacity>
						<offset>-0.05</offset>
					</li>
					<li>
						<capacity>Sight</capacity>
						<offset>-0.05</offset>
					</li>
					<li>
						<capacity>Manipulation</capacity>
						<offset>-0.05</offset>
					</li>
				</capMods>
				<hediffGivers>
					<li Class="Pawnmorph.HediffGiver_Mutation">
						<hediff>EtherSnakeJaw</hediff>
						<mtbDays>0.5</mtbDays>
						<partsToAffect>
							<li>Jaw</li>
						</partsToAffect>
						<tale><!--Needs Tale--></tale>
					</li>
					<li Class="Pawnmorph.HediffGiver_Mutation">
						<hediff>EtherSnakeHood</hediff>
						<mtbDays>1</mtbDays>
						<partsToAffect>
							<li>Head</li>
						</partsToAffect>
						<countToAffect>2</countToAffect>
						<tale><!--Needs Tale--></tale>
					</li>
					<li Class="Pawnmorph.HediffGiver_Mutation">
						<hediff>EtherSnakeTail</hediff>
						<mtbDays>1</mtbDays>
						<partsToAffect>
							<li>Tail</li>
						</partsToAffect>
						<tale><!--Needs Tale--></tale>
					</li>
					<li Class="Pawnmorph.HediffGiver_Mutation">
						<hediff>EtherScaledLimb</hediff>
						<mtbDays>2</mtbDays>
						<partsToAffect>
							<li>Arm</li>
						</partsToAffect>
						<countToAffect>2</countToAffect>
						<tale><!--Needs Tale--></tale>
					</li>
					<li Class="Pawnmorph.HediffGiver_Mutation">
						<hediff>EtherSnakeHand</hediff>
						<mtbDays>3</mtbDays>
						<chance>5</chance>
						<partsToAffect>
							<li>Hand</li>
						</partsToAffect>
						<countToAffect>2</countToAffect>
						<tale><!--Needs Tale--></tale>
						<memory><!--Needs Memory--></memory>
					</li>
					<li Class="Pawnmorph.HediffGiver_Mutation">
						<hediff>EtherSnakeEye</hediff>
						<mtbDays>1.5</mtbDays>
						<partsToAffect>
							<li>Eye</li>
						</partsToAffect>
						<countToAffect>2</countToAffect>
						<tale><!--Needs Tale--></tale>
					</li>
				</hediffGivers>
			</li>
		</stages>
	</HediffDef>
</Defs>